zhousflib/__init__.py
zhousflib/database/__init__.py
zhousflib/database/chromadb_master.py
zhousflib/database/lmdb_master.py
zhousflib/database/tinydb_master.py
zhousflib/datasets/__init__.py
zhousflib/datasets/classification/__init__.py
zhousflib/datasets/classification/classification_dataset_split.py
zhousflib/datasets/coco/__init__.py
zhousflib/datasets/coco/coco_bbox_extract.py
zhousflib/datasets/coco/coco_bbox_update.py
zhousflib/datasets/coco/coco_bbox_vis.py
zhousflib/datasets/coco/coco_dataset_merge.py
zhousflib/datasets/coco/coco_dataset_split.py
zhousflib/datasets/labelme/__init__.py
zhousflib/datasets/labelme/labelme_bbox_update.py
zhousflib/datasets/labelme/labelme_clip.py
zhousflib/datasets/labelme/labelme_convert_coco.py
zhousflib/datasets/labelme/labelme_convert_seg.py
zhousflib/datasets/labelme/labelme_convert_uiex.py
zhousflib/datasets/labelme/labelme_dataset_clip.py
zhousflib/datasets/labelme/shape_convert.py
zhousflib/datasets/segmentation/__init__.py
zhousflib/datasets/segmentation/seg_dataset_split.py
zhousflib/decorator/__init__.py
zhousflib/decorator/except_util.py
zhousflib/decorator/interceptor_util.py
zhousflib/docker/__init__.py
zhousflib/docker/build.py
zhousflib/draw/__init__.py
zhousflib/draw/drawer.py
zhousflib/file/__init__.py
zhousflib/file/delete_file.py
zhousflib/file/download_http.py
zhousflib/file/download_oss.py
zhousflib/file/download_requests.py
zhousflib/file/obs_huawei.py
zhousflib/file/zip_util.py
zhousflib/font/SimSun.ttf
zhousflib/font/Symbola.ttf
zhousflib/font/__init__.py
zhousflib/image/__init__.py
zhousflib/image/cv.py
zhousflib/image/nms_util.py
zhousflib/image/op.py
zhousflib/image/pil_util.py
zhousflib/image/similarity.py
zhousflib/infer_framework/__init__.py
zhousflib/infer_framework/ann/__init__.py
zhousflib/infer_framework/ann/onnx/__init__.py
zhousflib/infer_framework/ann/onnx/onnx_to_trt.py
zhousflib/infer_framework/ann/onnx/paddle_to_onnx.py
zhousflib/infer_framework/ann/tensorrt/__init__.py
zhousf_lib-1.6.8.5.7.dist-info/LICENSE
zhousf_lib-1.6.8.5.7.dist-info/METADATA
zhousf_lib-1.6.8.5.7.dist-info/WHEEL
zhousf_lib-1.6.8.5.7.dist-info/top_level.txt
zhousf_lib-1.6.8.5.7.dist-info/RECORD
